README.txt
setup.py
pipedrive/__init__.py
python_pipedrive.egg-info/PKG-INFO
python_pipedrive.egg-info/SOURCES.txt
python_pipedrive.egg-info/dependency_links.txt
python_pipedrive.egg-info/not-zip-safe
python_pipedrive.egg-info/requires.txt
python_pipedrive.egg-info/top_level.txt