Metadata-Version: 1.0
Name: python-pipedrive
Version: 0.1.2
Summary: Light wrapper around Pipedrive API
Home-page: http://github.com/jscott1989/python-pipedrive
Author: Jonathan Scott
Author-email: jonathanscott1989@gmail.com
License: MIT
Download-URL: http://github.com/jscott1989/python-pipedrive/downloads
Platform: UNKNOWN
Classifier: Development Status :: 3 - Alpha
Classifier: Environment :: Web Environment
Classifier: Intended Audience :: Developers
Classifier: Operating System :: OS Independent
Classifier: Programming Language :: Python
Classifier: Framework :: Django
